jupyterlab_notifications_extension/__init__.py
jupyterlab_notifications_extension/_version.py
jupyterlab_notifications_extension/cli.py
jupyterlab_notifications_extension/routes.py
jupyterlab_notifications_extension/tests/__init__.py
jupyterlab_notifications_extension/tests/test_routes.py
jupyterlab_notifications_extension-1.1.26.data/data/etc/jupyter/jupyter_server_config.d/jupyterlab_notifications_extension.json
jupyterlab_notifications_extension-1.1.26.data/data/share/jupyter/labextensions/jupyterlab_notifications_extension/package.json
jupyterlab_notifications_extension-1.1.26.data/data/share/jupyter/labextensions/jupyterlab_notifications_extension/static/728.a6a0c34a1c50618b9f7b.js
jupyterlab_notifications_extension-1.1.26.data/data/share/jupyter/labextensions/jupyterlab_notifications_extension/static/750.0c532b05a65a2f4e2f74.js
jupyterlab_notifications_extension-1.1.26.data/data/share/jupyter/labextensions/jupyterlab_notifications_extension/static/remoteEntry.336b6b06eecb1f10cf3d.js
jupyterlab_notifications_extension-1.1.26.data/data/share/jupyter/labextensions/jupyterlab_notifications_extension/static/style.js
jupyterlab_notifications_extension-1.1.26.data/data/share/jupyter/labextensions/jupyterlab_notifications_extension/static/third-party-licenses.json
jupyterlab_notifications_extension-1.1.26.data/data/share/jupyter/labextensions/jupyterlab_notifications_extension/install.json
jupyterlab_notifications_extension-1.1.26.dist-info/METADATA
jupyterlab_notifications_extension-1.1.26.dist-info/WHEEL
jupyterlab_notifications_extension-1.1.26.dist-info/entry_points.txt
jupyterlab_notifications_extension-1.1.26.dist-info/licenses/LICENSE
jupyterlab_notifications_extension-1.1.26.dist-info/RECORD
